minette_symphony/__init__.py
minette_symphony/symphonyadapter.py
minette_symphony/version.py
minette_symphony_adapter/__init__.py
minette_symphony_adapter/symphonyadapter.py
minette_symphony_adapter/version.py
minette_symphony-0.2.dist-info/LICENSE
minette_symphony-0.2.dist-info/METADATA
minette_symphony-0.2.dist-info/WHEEL
minette_symphony-0.2.dist-info/top_level.txt
minette_symphony-0.2.dist-info/RECORD
