Metadata-Version: 2.1
Name: minette-symphony
Version: 0.2
Summary: Adapter for Symphony to create chatbot using Minette framework.
Home-page: https://github.com/uezo/minette-symphony
Author: uezo
Author-email: uezo@uezo.net
Maintainer: uezo
Maintainer-email: uezo@uezo.net
License: MIT
Platform: UNKNOWN
Classifier: Programming Language :: Python :: 3
Requires-Dist: minette
Requires-Dist: sym-api-client-python
Requires-Dist: lxml
